JK/jk_flipflop.vhdl
library ieee;
use ieee.std_logic_1164.all;

entity jk_flipflop is
    port (
        J, K, CLK, RESET: in std_logic;
        Q, Q_bar: out std_logic
    );
end entity jk_flipflop;

architecture behavioral of jk_flipflop is
    signal internal_Q, internal_Q_bar: std_logic;
begin
    process (CLK, RESET)
    begin
        if (RESET = '1') then
            internal_Q <= '0';
            internal_Q_bar <= '1';
        elsif (rising_edge(CLK)) then
            if (J = '0' and K = '0') then
                internal_Q <= internal_Q;
                internal_Q_bar <= internal_Q_bar;
            elsif (J = '0' and K = '1') then
                internal_Q <= '0';
                internal_Q_bar <= '1';
            elsif (J = '1' and K = '0') then
                internal_Q <= '1';
                internal_Q_bar <= '0';
            elsif (J = '1' and K = '1') then
                internal_Q <= not internal_Q;
                internal_Q_bar <= not internal_Q_bar;
            end if;
        end if;
    end process;

    Q <= internal_Q;
    Q_bar <= internal_Q_bar;
end architecture behavioral;

JK/jk_flipflop_tb.vhdl
library ieee;
use ieee.std_logic_1164.all;

entity jk_flipflop_tb is
end entity jk_flipflop_tb;

architecture testbench of jk_flipflop_tb is
    component jk_flipflop
        port (
            J, K, CLK, RESET: in std_logic;
            Q, Q_bar: out std_logic
        );
    end component;

    signal J, K, CLK, RESET: std_logic;
    signal Q, Q_bar: std_logic;
begin
    uut: jk_flipflop
    port map (
        J => J,
        K => K,
        CLK => CLK,
        RESET => RESET,
        Q => Q,
        Q_bar => Q_bar
    );

    -- Clock process
    clk_process: process
    begin
        while now < 1000 ns loop
            CLK <= '0';
            wait for 5 ns;
            CLK <= '1';
            wait for 5 ns;
        end loop;
        wait;
    end process;

    -- Stimulus process
    stimulus_process: process
    begin
        -- Apply reset
        RESET <= '1';
        wait for 10 ns;
        RESET <= '0';

        -- Test JK flip-flop behavior
        wait for 20 ns;
        J <= '1'; K <= '0';  -- Set J=1, K=0
        wait for 10 ns;
        J <= '0'; K <= '1';  -- Set J=0, K=1
        wait for 10 ns;
        J <= '1'; K <= '1';  -- Set J=1, K=1
        wait for 10 ns;
        J <= '0'; K <= '0';  -- Set J=0, K=0
        wait for 10 ns;

        -- Finish simulation
        wait;
    end process;
end architecture testbench;

JK/result.vcd
$date
  Mon Feb 19 11:52:43 2024
$end
$version
  GHDL v0
$end
$timescale
  1 fs
$end
$scope module standard $end
$upscope $end
$scope module std_logic_1164 $end
$upscope $end
$scope module jk_flipflop_tb $end
$var reg 1 ! j $end
$var reg 1 " k $end
$var reg 1 # clk $end
$var reg 1 $ reset $end
$var reg 1 % q $end
$var reg 1 & q_bar $end
$scope module uut $end
$var reg 1 ' j $end
$var reg 1 ( k $end
$var reg 1 ) clk $end
$var reg 1 * reset $end
$var reg 1 + q $end
$var reg 1 , q_bar $end
$var reg 1 - internal_q $end
$var reg 1 . internal_q_bar $end
$upscope $end
$upscope $end
$enddefinitions $end
#0
U!
U"
0#
1$
0%
1&
U'
U(
0)
1*
0+
1,
0-
1.
#5000000
1#
1)
#10000000
0#
0$
0)
0*
#15000000
1#
1)
#20000000
0#
0)
#25000000
1#
1)
#30000000
1!
0"
0#
1'
0(
0)
#35000000
1#
1%
0&
1)
1+
0,
1-
0.
#40000000
0!
1"
0#
0'
1(
0)
#45000000
1#
0%
1&
1)
0+
1,
0-
1.
#50000000
1!
0#
1'
0)
#55000000
1#
1%
0&
1)
1+
0,
1-
0.
#60000000
0!
0"
0#
0'
0(
0)
